.hgignore
.hgtags
HISTORY.txt
README.txt
bootstrap.py
buildout-3.1.x.cfg
buildout-3.3.x.cfg
buildout-4.0.x.cfg
buildout.cfg
setup.py
Products/__init__.py
Products.BlingPortlet.egg-info/PKG-INFO
Products.BlingPortlet.egg-info/SOURCES.txt
Products.BlingPortlet.egg-info/dependency_links.txt
Products.BlingPortlet.egg-info/entry_points.txt
Products.BlingPortlet.egg-info/namespace_packages.txt
Products.BlingPortlet.egg-info/not-zip-safe
Products.BlingPortlet.egg-info/requires.txt
Products.BlingPortlet.egg-info/top_level.txt
Products/BlingPortlet/__init__.py
Products/BlingPortlet/adapter.py
Products/BlingPortlet/bling-slider.css
Products/BlingPortlet/bling-slider.js
Products/BlingPortlet/bling.pt
Products/BlingPortlet/bling.py
Products/BlingPortlet/configure.zcml
Products/BlingPortlet/content.py
Products/BlingPortlet/interfaces.py
Products/BlingPortlet/linkableimage.pt
Products/BlingPortlet/linkableimage_icon.gif
Products/BlingPortlet/meta.zcml
Products/BlingPortlet/metaconfigure.py
Products/BlingPortlet/slideshow.pt
Products/BlingPortlet/version.txt
Products/BlingPortlet/vocabularies.py
Products/BlingPortlet/profiles/default/cssregistry.xml
Products/BlingPortlet/profiles/default/jsregistry.xml
Products/BlingPortlet/profiles/default/metadata.xml
Products/BlingPortlet/profiles/default/portlets.xml
Products/BlingPortlet/profiles/default/propertiestool.xml
Products/BlingPortlet/profiles/default/rolemap.xml
Products/BlingPortlet/profiles/default/types.xml
Products/BlingPortlet/profiles/default/workflows.xml
Products/BlingPortlet/profiles/default/types/Linkable_Image.xml
Products/BlingPortlet/tests/__init__.py
Products/BlingPortlet/tests/base.py
Products/BlingPortlet/tests/test.gif
Products/BlingPortlet/tests/test_adapter.py
Products/BlingPortlet/tests/test_bling_portlet.py
Products/BlingPortlet/tests/test_bling_slideshow_portlet.py