Metadata-Version: 1.1
Name: Products.BlingPortlet
Version: 2.1
Summary: A portlet that adds bling to your site
Home-page: http://weblion.psu.edu/
Author: WebLion Documentation Group, Penn State University
Author-email: support@weblion.psu.edu
License: GPL
Platform: UNKNOWN
Classifier: Framework :: Plone
Classifier: Programming Language :: Python
Classifier: Topic :: Software Development :: Libraries :: Python Modules
